<content>

    <id>
        709
    </id>

    <foodname>
        早糯谷
    </foodname>

    <firstcategory>
        米面豆乳类
    </firstcategory>

    <secondcategory>
        
    </secondcategory>

    <alias>
        糯米、江米
    </alias>

    <season>
        夏
    </season>

    <unsuit>

    </unsuit>

    <suit>

    </suit>

    <ingredient>
    </ingredient>

    <introduction>
        <rawdata>
            糯米是糯谷脱壳的米，在中国南方称为糯米，而北方则多称为江米。是制造粘性小吃，各式甜品的主要原料，糯米也是酿造醪糟（甜米酒）的主要原料。
        </rawdata>

        <segment>
            糯米  是  糯谷  脱壳  的  米  ，  在  中国  南方  称为  糯米  ，  而  北方  则  多  称为  江米  。  是  制造  粘性  小吃  ，  各  式  甜品  的  主要  原料  ，  糯米  也  是  酿造  醪糟  （  甜  米酒  ）  的  主要  原料  。
        </segment>

        <pos>
            糯米#NN  是#VC  糯谷#VV  脱壳#NN  的#DEC  米#M  ，#PU  在#P  中国#NR  南方#NN  称为#VV  糯米#NN  ，#PU  而#CC  北方#NN  则#AD  多#AD  称为#VV  江米#NN    。#PU  是#VC  制造#NN  粘性#NN  小吃#NN  ，#PU  各#DT  式#M  甜品#NN  的#DEG  主要#JJ  原料#NN  ，#PU  糯米#AD  也#AD  是#VC  酿造#VV  醪糟#NN  （#PU  甜#AD  米酒#VV  ）#PU  的#DEC  主要#JJ  原料#NN    。#PU
        </pos>

        <parsing>
            (nsubj, 糯谷#VV, 糯米#NN)  (cop, 糯谷#VV, 是#VC)  (root, ROOT#null, 糯谷#VV)  (dobj, 糯谷#VV, 脱壳#NN)  (mark, 糯谷#VV, 的#DEC)  (dep, 糯谷#VV, 米#M)  (case, 南方#NN, 在#P)  (nn, 南方#NN, 中国#NR)  (prep, 称为#VV, 南方#NN)  (conj, 糯谷#VV, 称为#VV)  (dobj, 称为#VV, 糯米#NN)  (cc, 糯谷#VV, 而#CC)  (nsubj, 称为#VV, 北方#NN)  (advmod, 称为#VV, 则#AD)  (advmod, 称为#VV, 多#AD)  (conj, 糯谷#VV, 称为#VV)  (dobj, 称为#VV, 江米#NN)   (cop, 小吃#NN, 是#VC)  (nn, 小吃#NN, 制造#NN)  (nn, 小吃#NN, 粘性#NN)  (root, ROOT#null, 小吃#NN)  (det, 甜品#NN, 各#DT)  (clf, 各#DT, 式#M)  (assmod, 原料#NN, 甜品#NN)  (case, 甜品#NN, 的#DEG)  (amod, 原料#NN, 主要#JJ)  (dep, 原料#NN, 原料#NN)  (advmod, 原料#NN, 糯米#AD)  (advmod, 原料#NN, 也#AD)  (cop, 原料#NN, 是#VC)  (relcl, 原料#NN, 酿造#VV)  (dobj, 酿造#VV, 醪糟#NN)  (advmod, 米酒#VV, 甜#AD)  (dep, 酿造#VV, 米酒#VV)  (mark, 酿造#VV, 的#DEC)  (amod, 原料#NN, 主要#JJ)  (conj, 小吃#NN, 原料#NN)
        </parsing>

        <tag>
            糯谷脱壳  称为糯米  称为江米  制造小吃  粘性小吃  酿造原料  酿造醪糟  
        </tag>
    </introduction>

    <effect>
        <rawdata>
            糯米味甘、性温，入脾、胃、肺经；具有补中益气，健脾养胃，止虚汗之功效。
        </rawdata>

        <segment>
            糯米  味  甘  、  性温  ，  入脾  、  胃  、  肺经  ；  具有  补  中  益气  ，  健脾  养  胃  ，  止  虚汗  之  功效  。
        </segment>

        <pos>
            糯米#NN  味#VV  甘#NR  、#PU  性温#NR  ，#PU  入脾#NR  、#PU  胃#NR  、#PU  肺经#NR  ；#PU  具有#VV  补#NN  中#LC  益气#NN  ，#PU  健脾#AD  养#VV  胃#NN  ，#PU  止#VV  虚汗#NN  之#DEG  功效#NN  。#PU
        </pos>

        <parsing>
            (nsubj, 味#VV, 糯米#NN)  (root, ROOT#null, 味#VV)  (conj, 肺经#NR, 甘#NR)  (dep, 肺经#NR, 性温#NR)  (conj, 肺经#NR, 入脾#NR)  (conj, 肺经#NR, 胃#NR)  (dobj, 味#VV, 肺经#NR)  (conj, 味#VV, 具有#VV)  (dep, 益气#NN, 补#NN)  (case, 补#NN, 中#LC)  (dobj, 具有#VV, 益气#NN)  (advmod, 养#VV, 健脾#AD)  (conj, 味#VV, 养#VV)  (dobj, 养#VV, 胃#NN)  (conj, 味#VV, 止#VV)  (assmod, 功效#NN, 虚汗#NN)  (case, 虚汗#NN, 之#DEG)  (dobj, 止#VV, 功效#NN)
        </parsing>

        <tag>
            肺经  入脾  
        </tag>
    </effect>

    <manuleffecttag>
        补气  健脾止泻  温中
    </manuleffecttag>

    <nutrition>
        <rawdata>
            1、糯米含有蛋白质、脂肪、糖类、钙、磷、铁、维生素B1、维生索B2、烟酸及淀粉等。
        </rawdata>

        <segment>
            糯米  含有  蛋白质  、  脂肪  、  糖类  、  钙  、  磷  、  铁  、  维生素B1  、  维生  索  B2  、  烟酸  及  淀粉  等  。
        </segment>

        <pos>
            糯米#AD  含有#VV  蛋白质#NN  、#PU  脂肪#NN  、#PU  糖类#NN  、#PU  钙#NN  、#PU  磷#NN  、#PU  铁#NN  、#PU  维生素B1#CD  、#PU  维生#AD  索#VV  B2#CD  、#PU  烟酸#CD  及#CC  淀粉#CD  等#ETC  。#PU
        </pos>

        <parsing>
            (advmod, 含有#VV, 糯米#AD)  (root, ROOT#null, 含有#VV)  (conj, 铁#NN, 蛋白质#NN)  (conj, 铁#NN, 脂肪#NN)  (conj, 铁#NN, 糖类#NN)  (conj, 铁#NN, 钙#NN)  (conj, 铁#NN, 磷#NN)  (dobj, 含有#VV, 铁#NN)  (conj, 含有#VV, 维生素B1#CD)  (advmod, 索#VV, 维生#AD)  (conj, 含有#VV, 索#VV)  (nummod, 淀粉#CD, B2#CD)  (nummod, 淀粉#CD, 烟酸#CD)  (cc, 淀粉#CD, 及#CC)  (range, 索#VV, 淀粉#CD)  (dep, 含有#VV, 等#ETC)
        </parsing>

        <tag>
            含有铁  
        </tag>
    </nutrition>

    <cuisine>
        <rawdata>
            宜加热后食用；宜煮稀薄粥服食，不仅营养滋补，还极易消化吸收，养胃气。
        </rawdata>

        <segment>
            宜  加热  后  食用  ；  宜  煮  稀薄  粥  服食  ，  不仅  营养  滋补  ，  还  极易  消化  吸收  ，  养  胃  气  。
        </segment>

        <pos>
            宜#NR  加热#NN  后#LC  食用#VV  ；#PU  宜#NR  煮#VV  稀薄#NN  粥#NN  服食#NN  ，#PU  不仅#CC  营养#VA  滋补#VA  ，#PU  还#AD  极易#VV  消化#NN  吸收#NN  ，#PU  养#VV  胃#NN  气#NN  。#PU
        </pos>

        <parsing>
            (nsubj, 食用#VV, 宜#NR)  (loc, 食用#VV, 加热#NN)  (case, 加热#NN, 后#LC)  (root, ROOT#null, 食用#VV)  (nsubj, 煮#VV, 宜#NR)  (conj, 食用#VV, 煮#VV)  (nn, 服食#NN, 稀薄#NN)  (nn, 服食#NN, 粥#NN)  (dobj, 煮#VV, 服食#NN)  (cc, 煮#VV, 不仅#CC)  (conj, 煮#VV, 营养#VA)  (comod, 营养#VA, 滋补#VA)  (advmod, 极易#VV, 还#AD)  (conj, 煮#VV, 极易#VV)  (nn, 吸收#NN, 消化#NN)  (dobj, 极易#VV, 吸收#NN)  (conj, 煮#VV, 养#VV)  (nn, 气#NN, 胃#NN)  (dobj, 养#VV, 气#NN)
        </parsing>

        <tag>
            食用  稀薄服食  滋补营养  消化吸收  极易吸收  
        </tag>
    </cuisine>

    <pictureweburl>
        http://recipe1.hoto.cn/pic/fooddata/eb/40/82155_120.jpg
    </pictureweburl>

    <picturelocalurl>
        .\pictures\709 早糯谷.jpg
    </picturelocalurl>

</content>
