<content>

    <id>
        981
    </id>

    <foodname>
        颚针鱼
    </foodname>

    <firstcategory>
        水产品
    </firstcategory>

    <secondcategory>
        
    </secondcategory>

    <alias>
        针量鱼
    </alias>

    <season>
        
    </season>

    <unsuit>

    </unsuit>

    <suit>

    </suit>

    <ingredient>

    </ingredient>

    <introduction>
        <rawdata>
            硬骨鱼纲颚针鱼目颚针鱼科鱼类的通称。约有10属32种。中华人民共和国有3属8种。体长一般达0.4～0.8米，最大者可达1.2米以上；体延长，圆柱状，被细小圆鳞；两颌皆延长成细长针喙状，下颌稍较长；两颌具细小尖齿，呈带状排列，并各具一行稀疏的犬齿；鳃孔宽阔，鳃盖膜不与鳃峡相连；下咽骨愈合成一窄长的平板，被有细小尖齿；有前筛骨；背鳍与臀鳍长，基本相对，均远位于体的后部；侧线低，邻近腹缘。分布于印度洋、太平洋和大西洋的热带及暖温带海区。栖息于近海或河口，为上层凶猛鱼，主要以小型鱼类和幼鱼以及无脊椎动物等为食。此类鱼肉稍带酸味，食用价值不大。
        </rawdata>

        <segment>
            硬骨鱼  纲颚  针  鱼目  颚针  鱼科  鱼类  的  通称  。  约  有  属  32  种  。  中华  人民  共和国  有  3  属  8  种  。  体长  一般  达  0.4～0.8  米  ，  最  大  者  可  达  1.2  米  以上  ；  体  延长  ，  圆柱状  ，  被  细小  圆鳞  ；  两  颌  皆  延长  成  细长  针喙状  ，  下颌  稍  较长  ；  两  颌  具  细小  尖齿  ，  呈  带状  排列  ，  并  各  具  一行  稀疏  的  犬齿  ；  鳃孔  宽阔  ，  鳃盖  膜  不  与  鳃峡  相连  ；  下  咽  骨  愈合  成  一  窄  长  的  平板  ，  被  有  细小  尖齿  ；  有前  筛骨  ；  背鳍  与  臀鳍  长  ，  基本  相对  ，  均  远  位于  体  的  后部  ；  侧线  低  ，  邻近  腹缘  。  分布  于  印度洋  、  太平洋  和  大西洋  的  热带  及  暖  温带  海区  。  栖息于  近海  或  河口  ，  为  上层  凶猛  鱼  ，  主要  以  小型  鱼类  和  幼鱼  以及  无脊椎  动物  等  为食  。  此  类  鱼肉  稍带  酸味  ，  食用  价值  不大  。
        </segment>

        <pos>
            硬骨鱼#NN  纲颚#NN  针#NN  鱼目#VV  颚针#NN  鱼科#NN  鱼类#NN  的#DEG  通称#NN    。#PU  约#AD  有#VE  属#VV  32#CD  种#M    。#PU  中华#NR  人民#NN  共和国#NN  有#VE  3#CD  属#VV  8#CD  种#M    。#PU  体长#NR  一般#AD  达#VV  0.4#CD  ～#NN  0.8#CD  米#M  ，#PU  最#AD  大#JJ  者#NN  可#VV  达#VV  1.2#CD  米#M  以上#LC  ；#PU  体#NR  延长#VV  ，#PU  圆柱状#NR  ，#PU  被#SB  细小#VV  圆鳞#NN  ；#PU  两#CD  颌#NN  皆#AD  延长#VV  成#VV  细长#NN  针喙状#NN  ，#PU  下颌#VV  稍#NN  较长#NN  ；#PU  两#CD  颌#NN  具#VV  细小#NN  尖齿#NN  ，#PU  呈#VV  带状#NN  排列#NN  ，#PU  并#CC  各#AD  具#VV  一行#NN  稀疏#NN  的#DEG  犬齿#NN  ；#PU  鳃孔#NR  宽阔#VA  ，#PU  鳃盖#NN  膜#NN  不#AD  与#P  鳃峡#NR  相连#VV  ；#PU  下#DT  咽#CD  骨#NN  愈合#AD  成#VV  一#CD  窄#VA  长#VA  的#DEC  平板#NN  ，#PU  被#SB  有#VE  细小#NN  尖齿#NN  ；#PU  有前#VV  筛骨#NN  ；#PU  背鳍#NR  与#P  臀鳍#NN  长#NN  ，#PU  基本#AD  相对#AD  ，#PU  均#AD  远#AD  位于#VV  体#NR  的#DEG  后部#NN  ；#PU  侧线#NR  低#VA  ，#PU  邻近#VA  腹缘#VA    。#PU  分布#VV  于#P  印度洋#NR  、#PU  太平洋#NR  和#CC  大西洋#NR  的#DEC  热带#NN  及#CC  暖#NN  温带#VV  海区#NN    。#PU  栖息于#VV  近海#NN  或#CC  河口#NR  ，#PU  为#P  上层#NN  凶猛#VA  鱼#NN  ，#PU  主要#AD  以#P  小型#JJ  鱼类#NN  和#CC  幼鱼#NN  以及#CC  无脊椎#JJ  动物#NN  等#ETC  为食#VV    。#PU  此#DT  类#M  鱼肉#NN  稍带#NN  酸味#VV  ，#PU  食用#VV  价值#NN  不大#NN    。#PU
        </pos>

        <parsing>
            (nn, 针#NN, 硬骨鱼#NN)  (nn, 针#NN, 纲颚#NN)  (nsubj, 鱼目#VV, 针#NN)  (root, ROOT#null, 鱼目#VV)  (nn, 鱼类#NN, 颚针#NN)  (nn, 鱼类#NN, 鱼科#NN)  (assmod, 通称#NN, 鱼类#NN)  (case, 鱼类#NN, 的#DEG)  (dobj, 鱼目#VV, 通称#NN)   (advmod, 有#VE, 约#AD)  (root, ROOT#null, 有#VE)  (dep, 有#VE, 属#VV)  (nummod, 种#M, 32#CD)  (range, 属#VV, 种#M)   (nn, 共和国#NN, 中华#NR)  (nn, 共和国#NN, 人民#NN)  (dep, 有#VE, 共和国#NN)  (root, ROOT#null, 有#VE)  (nsubj, 属#VV, 3#CD)  (dep, 有#VE, 属#VV)  (nummod, 种#M, 8#CD)  (range, 属#VV, 种#M)   (nsubj, 达#VV, 体长#NR)  (advmod, 达#VV, 一般#AD)  (dep, 腹缘#VA, 达#VV)  (nummod, ～#NN, 0.4#CD)  (nummod, 米#M, 0.8#CD)  (range, 达#VV, 米#M)  (advmod, 大#JJ, 最#AD)  (amod, 者#NN, 大#JJ)  (nsubj, 可#VV, 者#NN)  (conj, 达#VV, 可#VV)  (rcomp, 可#VV, 达#VV)  (nummod, 米#M, 1.2#CD)  (loc, 可#VV, 米#M)  (case, 米#M, 以上#LC)  (nsubj, 延长#VV, 体#NR)  (conj, 达#VV, 延长#VV)  (dep, 细小#VV, 圆柱状#NR)  (auxpass, 细小#VV, 被#SB)  (ccomp, 延长#VV, 细小#VV)  (dobj, 细小#VV, 圆鳞#NN)  (nummod, 颌#NN, 两#CD)  (nsubj, 成#VV, 颌#NN)  (advmod, 成#VV, 皆#AD)  (mmod, 成#VV, 延长#VV)  (conj, 达#VV, 成#VV)  (nn, 针喙状#NN, 细长#NN)  (dobj, 成#VV, 针喙状#NN)  (conj, 达#VV, 下颌#VV)  (nn, 较长#NN, 稍#NN)  (dobj, 下颌#VV, 较长#NN)  (nummod, 颌#NN, 两#CD)  (nsubj, 具#VV, 颌#NN)  (conj, 达#VV, 具#VV)  (nn, 尖齿#NN, 细小#NN)  (dobj, 具#VV, 尖齿#NN)  (conj, 具#VV, 呈#VV)  (nn, 排列#NN, 带状#NN)  (dobj, 呈#VV, 排列#NN)  (cc, 具#VV, 并#CC)  (advmod, 具#VV, 各#AD)  (conj, 具#VV, 具#VV)  (nn, 稀疏#NN, 一行#NN)  (assmod, 犬齿#NN, 稀疏#NN)  (case, 稀疏#NN, 的#DEG)  (dobj, 具#VV, 犬齿#NN)  (nsubj, 宽阔#VA, 鳃孔#NR)  (conj, 达#VV, 宽阔#VA)  (nn, 膜#NN, 鳃盖#NN)  (nsubj, 相连#VV, 膜#NN)  (neg, 相连#VV, 不#AD)  (case, 鳃峡#NR, 与#P)  (prep, 相连#VV, 鳃峡#NR)  (conj, 达#VV, 相连#VV)  (det, 骨#NN, 下#DT)  (dep, 下#DT, 咽#CD)  (nsubj, 成#VV, 骨#NN)  (advmod, 成#VV, 愈合#AD)  (conj, 达#VV, 成#VV)  (nummod, 平板#NN, 一#CD)  (relcl, 平板#NN, 窄#VA)  (comod, 窄#VA, 长#VA)  (mark, 窄#VA, 的#DEC)  (dobj, 成#VV, 平板#NN)  (auxpass, 有#VE, 被#SB)  (conj, 达#VV, 有#VE)  (nn, 尖齿#NN, 细小#NN)  (dobj, 有#VE, 尖齿#NN)  (conj, 达#VV, 有前#VV)  (dobj, 有前#VV, 筛骨#NN)  (nsubj, 位于#VV, 背鳍#NR)  (case, 长#NN, 与#P)  (nn, 长#NN, 臀鳍#NN)  (prep, 位于#VV, 长#NN)  (advmod, 位于#VV, 基本#AD)  (advmod, 位于#VV, 相对#AD)  (advmod, 位于#VV, 均#AD)  (advmod, 位于#VV, 远#AD)  (conj, 达#VV, 位于#VV)  (assmod, 后部#NN, 体#NR)  (case, 体#NR, 的#DEG)  (dobj, 位于#VV, 后部#NN)  (nsubj, 低#VA, 侧线#NR)  (conj, 达#VV, 低#VA)  (conj, 达#VV, 邻近#VA)  (root, ROOT#null, 腹缘#VA)   (relcl, 暖#NN, 分布#VV)  (case, 大西洋#NR, 于#P)  (conj, 大西洋#NR, 印度洋#NR)  (conj, 大西洋#NR, 太平洋#NR)  (cc, 大西洋#NR, 和#CC)  (prep, 分布#VV, 大西洋#NR)  (mark, 分布#VV, 的#DEC)  (conj, 暖#NN, 热带#NN)  (cc, 暖#NN, 及#CC)  (nsubj, 温带#VV, 暖#NN)  (root, ROOT#null, 温带#VV)  (dobj, 温带#VV, 海区#NN)   (root, ROOT#null, 栖息于#VV)  (conj, 河口#NR, 近海#NN)  (cc, 河口#NR, 或#CC)  (dobj, 栖息于#VV, 河口#NR)  (case, 上层#NN, 为#P)  (prep, 凶猛#VA, 上层#NN)  (conj, 栖息于#VV, 凶猛#VA)  (nsubj, 为食#VV, 鱼#NN)  (advmod, 为食#VV, 主要#AD)  (case, 动物#NN, 以#P)  (amod, 幼鱼#NN, 小型#JJ)  (conj, 幼鱼#NN, 鱼类#NN)  (cc, 幼鱼#NN, 和#CC)  (conj, 动物#NN, 幼鱼#NN)  (cc, 动物#NN, 以及#CC)  (amod, 动物#NN, 无脊椎#JJ)  (prep, 为食#VV, 动物#NN)  (etc, 动物#NN, 等#ETC)  (dep, 栖息于#VV, 为食#VV)   (det, 鱼肉#NN, 此#DT)  (clf, 此#DT, 类#M)  (nn, 稍带#NN, 鱼肉#NN)  (nsubj, 酸味#VV, 稍带#NN)  (root, ROOT#null, 酸味#VV)  (ccomp, 酸味#VV, 食用#VV)  (nn, 不大#NN, 价值#NN)  (dobj, 食用#VV, 不大#NN)
        </parsing>

        <tag>

        </tag>
    </introduction>

    <effect>

    </effect>

    <manuleffecttag>
        补中益气  健脾利湿
    </manuleffecttag>

    <nutrition>

    </nutrition>

    <cuisine>

    </cuisine>

    <pictureweburl>
        http://recipe1.hoto.cn/pic/fooddata/03/42/82435_120.jpg
    </pictureweburl>

    <picturelocalurl>
        .\pictures\981 颚针鱼.jpg
    </picturelocalurl>

</content>
