<content>

    <id>
        841
    </id>

    <foodname>
        北凤菌
    </foodname>

    <firstcategory>
        蔬菜类
    </firstcategory>

    <secondcategory>
        
    </secondcategory>

    <alias>
        皇蘑、北风菌、榆黄蘑、金顶蘑、榆蘑
    </alias>

    <season>
        
    </season>

    <unsuit>

    </unsuit>

    <suit>

    </suit>

    <ingredient>
    </ingredient>

    <introduction>
        北风菌属伞菌目，侧耳科。平菇是日常食用菌中最普通的一种，平菇菌盖为贝壳状或扇状，直径4～12厘米，幼时为青灰色或暗类色，后变成浅灰色或黄褐色，老时黄色；菌柄侧生或偏生，长1-3厘米，菌面平而薄，边缘不内卷，平展，菌褶粗疏。肉质较不老，嫩滑可口，有类似牡蛎的香味。
    </introduction>

    <effect>
        <rawdata>
            祛脂降压,养肝,提高免疫力,抑癌抗瘤、抑制癌细胞生长及扩散的作用。
        </rawdata>

        <tag>
            祛脂养肝  降压养肝  提高  抑癌抗瘤  癌细胞生长  抑制生长  
        </tag>
    </effect>

    <manuleffecttag>
        改善生长发育  辅助降血脂  抗癌防癌
    </manuleffecttag>

    <nutrition>

    </nutrition>

    <cuisine>
        北风菌的鲜品出水比较多，易被炒老、所以需要掌握好火候。
    </cuisine>

    <pictureweburl>
        http://recipe1.hoto.cn/pic/fooddata/75/41/82293_120.jpg
    </pictureweburl>

    <picturelocalurl>
        .\pictures\841 北凤菌.jpg
    </picturelocalurl>

</content>
