<content>

    <id>
        84
    </id>

    <foodname>
        带鱼
    </foodname>

    <firstcategory>
        鱼类
    </firstcategory>

    <secondcategory>
        咸水鱼
    </secondcategory>

    <alias>
        刀鱼、裙带鱼、牙带、白带鱼、柳鞭鱼、带柳、晦刀鱼
    </alias>

    <season>
        
    </season>

    <unsuit>
        <rawdata>
            1.患有疥疮、湿疹等皮肤病或皮肤过敏者忌食；2.癌症患者及红斑性狼疮之人忌食；3.痈疖疗毒和淋巴结核、支气管哮喘者亦忌之。
        </rawdata>

        <segment>
            患有  疥疮  、  湿疹  等  皮肤病  或  皮肤  过敏  者  忌食  ；  2  .  癌症  患者  及  红斑  性  狼疮  之  人  忌食  ；  3  .  痈疖  疗毒  和  淋巴  结核  、  支  气管  哮喘  者  亦  忌之  。
        </segment>

        <pos>
            患有#NN  疥疮#NN  、#PU  湿疹#NN  等#ETC  皮肤病#NN  或#CC  皮肤#NN  过敏#VV  者#NN  忌食#NN  ；#PU  2#CD  .#NN  癌症#NN  患者#NN  及#CC  红斑#NN  性#NN  狼疮#NN  之#DEG  人#NN  忌食#VA  ；#PU  3#CD  .#NN  痈疖#NN  疗毒#NN  和#CC  淋巴#NN  结核#NN  、#PU  支#M  气管#NN  哮喘#NN  者#NN  亦#AD  忌之#VV  。#PU
        </pos>

        <parsing>
            (nn, 湿疹#NN, 患有#NN)  (conj, 湿疹#NN, 疥疮#NN)  (nn, 皮肤#NN, 湿疹#NN)  (etc, 湿疹#NN, 等#ETC)  (conj, 皮肤#NN, 皮肤病#NN)  (cc, 皮肤#NN, 或#CC)  (nsubj, 过敏#VV, 皮肤#NN)  (root, ROOT#null, 过敏#VV)  (nn, 忌食#NN, 者#NN)  (dobj, 过敏#VV, 忌食#NN)  (nummod, 性#NN, 2#CD)  (nn, 性#NN, 癌症#NN)  (conj, 性#NN, 患者#NN)  (cc, 性#NN, 及#CC)  (nn, 性#NN, 红斑#NN)  (nn, 狼疮#NN, 性#NN)  (assmod, 人#NN, 狼疮#NN)  (case, 狼疮#NN, 之#DEG)  (nsubj, 忌食#VA, 人#NN)  (conj, 过敏#VV, 忌食#VA)  (nummod, 结核#NN, 3#CD)  (nn, 结核#NN, 痈疖#NN)  (conj, 结核#NN, 疗毒#NN)  (cc, 结核#NN, 和#CC)  (nn, 结核#NN, 淋巴#NN)  (conj, 者#NN, 结核#NN)  (clf, 者#NN, 支#M)  (nn, 者#NN, 气管#NN)  (nn, 者#NN, 哮喘#NN)  (nsubj, 忌之#VV, 者#NN)  (advmod, 忌之#VV, 亦#AD)  (conj, 过敏#VV, 忌之#VV)
        </parsing>

        <tag>
            
        </tag>
    </unsuit>

    <suit>
        <rawdata>
            一般人群均可食用。适宜久病体虚，血虚头晕，气短乏力，食少赢瘦，营养不良之人食用；适宜皮肤干燥之人食用。
        </rawdata>

        <segment>
            一般  人群  均  可  食用  。  适宜  久  病体  虚  ，  血虚  头晕  ，  气短  乏力  ，  食少  赢瘦  ，  营养  不良  之  人  食用  ；  适宜  皮肤  干燥  之  人  食用  。
        </segment>

        <pos>
            一般#JJ  人群#NN  均#AD  可#VV  食用#VV    。#PU  适宜#VA  久#VA  病体#VA  虚#AD  ，#PU  血虚#VV  头晕#NN  ，#PU  气短#VV  乏力#NN  ，#PU  食少#VV  赢瘦#NN  ，#PU  营养#VA  不良#JJ  之#DEG  人#NN  食用#VV  ；#PU  适宜#VV  皮肤#NN  干燥#NN  之#DEC  人#NN  食用#VV    。#PU
        </pos>

        <parsing>
            (amod, 人群#NN, 一般#JJ)  (nsubj, 食用#VV, 人群#NN)  (advmod, 食用#VV, 均#AD)  (dep, 食用#VV, 可#VV)  (root, ROOT#null, 食用#VV)   (relcl, 人#NN, 适宜#VA)  (comod, 适宜#VA, 久#VA)  (comod, 适宜#VA, 病体#VA)  (advmod, 血虚#VV, 虚#AD)  (ccomp, 适宜#VA, 血虚#VV)  (dobj, 血虚#VV, 头晕#NN)  (conj, 血虚#VV, 气短#VV)  (dobj, 气短#VV, 乏力#NN)  (conj, 血虚#VV, 食少#VV)  (dobj, 食少#VV, 赢瘦#NN)  (conj, 适宜#VA, 营养#VA)  (assmod, 人#NN, 不良#JJ)  (case, 不良#JJ, 之#DEG)  (dobj, 营养#VA, 人#NN)  (conj, 营养#VA, 食用#VV)  (dep, 适宜#VA, 适宜#VV)  (nn, 干燥#NN, 皮肤#NN)  (dobj, 适宜#VV, 干燥#NN)  (mark, 适宜#VA, 之#DEC)  (nsubj, 食用#VV, 人#NN)  (root, ROOT#null, 食用#VV)
        </parsing>

        <tag>
            
        </tag>
    </suit>

    <ingredient>
        <element>
            <elename>
                热量（大卡）
            </elename>
            <elevalue>
                127
            </elevalue>
        </element>
        <element>
            <elename>
                蛋白质（克）
            </elename>
            <elevalue>
                17.7
            </elevalue>
        </element>
        <element>
            <elename>
                脂肪（克）
            </elename>
            <elevalue>
                4.9
            </elevalue>
        </element>
        <element>
            <elename>
                碳水化合物（克）
            </elename>
            <elevalue>
                3.1
            </elevalue>
        </element>
        <element>
            <elename>
                胆固醇（毫克）
            </elename>
            <elevalue>
                76
            </elevalue>
        </element>
        <element>
            <elename>
                维生素A（微克）
            </elename>
            <elevalue>
                29
            </elevalue>
        </element>
        <element>
            <elename>
                维生素B1（毫克）
            </elename>
            <elevalue>
                0.02
            </elevalue>
        </element>
        <element>
            <elename>
                维生素B2（毫克）
            </elename>
            <elevalue>
                0.06
            </elevalue>
        </element>
        <element>
            <elename>
                烟酸（毫克）
            </elename>
            <elevalue>
                2.8
            </elevalue>
        </element>
        <element>
            <elename>
                维生素E（毫克）
            </elename>
            <elevalue>
                0.82
            </elevalue>
        </element>
        <element>
            <elename>
                钙（毫克）
            </elename>
            <elevalue>
                28
            </elevalue>
        </element>
        <element>
            <elename>
                磷（毫克）
            </elename>
            <elevalue>
                191
            </elevalue>
        </element>
        <element>
            <elename>
                钾（毫克）
            </elename>
            <elevalue>
                280
            </elevalue>
        </element>
        <element>
            <elename>
                钠（毫克）
            </elename>
            <elevalue>
                150.1
            </elevalue>
        </element>
        <element>
            <elename>
                镁（毫克）
            </elename>
            <elevalue>
                43
            </elevalue>
        </element>
        <element>
            <elename>
                铁（毫克）
            </elename>
            <elevalue>
                1.2
            </elevalue>
        </element>
        <element>
            <elename>
                锌（毫克）
            </elename>
            <elevalue>
                0.7
            </elevalue>
        </element>
        <element>
            <elename>
                碘（微克）
            </elename>
            <elevalue>
                5.5
            </elevalue>
        </element>
        <element>
            <elename>
                硒（微克）
            </elename>
            <elevalue>
                36.57
            </elevalue>
        </element>
        <element>
            <elename>
                铜（毫克）
            </elename>
            <elevalue>
                0.08
            </elevalue>
        </element>
        <element>
            <elename>
                锰（毫克）
            </elename>
            <elevalue>
                0.17
            </elevalue>
        </element>
    </ingredient>

    <introduction>
        <rawdata>
            带鱼体长扁侧呈带状，头窄长，口大、且尖，牙锋利，眼大位高，尾部细鞭状。体表银灰度色，无鳞，但表面有一层银粉，侧浅在胸鳍上方向后显著弯下沿腹线直达尾端，背鳍极长，无腹鳍。带鱼肉多且细，脂肪较多且集中于体外层，味鲜美，刺较少，但腹部有游离的小刺。我国沿海均产，以东海产量最大，南海产量较少，浙江、山东沿海是产量较多的二个海区。11-12月是盛产带鱼的季节。
        </rawdata>

        <segment>
            带鱼  体长  扁侧呈  带状  ，  头  窄  长  ，  口  大  、  且尖  ，  牙  锋利  ，  眼  大  位高  ，  尾部  细  鞭状  。  体表  银灰度色  ，  无鳞  ，  但  表面  有  一  层  银粉  ，  侧浅  在  胸鳍  上方  向后  显著  弯下  沿  腹  线  直达  尾端  ，  背鳍  极  长  ，  无  腹鳍  。  带鱼  肉  多  且  细  ，  脂肪  较多  且  集中  于  体外层  ，  味  鲜美  ，  刺较  少  ，  但  腹部  有  游离  的  小刺  。  我国  沿海  均  产  ，  以  东海  产量  最  大  ，  南海  产量  较  少  ，  浙江  、  山东  沿海  是  产量  较  多  的  二  个  海区  。  11  -  12月  是  盛产  带鱼  的  季节  。
        </segment>

        <pos>
            带鱼#NN  体长#NN  扁侧呈#NN  带状#NN  ，#PU  头#NN  窄#VA  长#VA  ，#PU  口#NN  大#VA  、#PU  且尖#VA  ，#PU  牙#NR  锋利#VV  ，#PU  眼#NN  大#JJ  位高#NN  ，#PU  尾部#AD  细#VV  鞭状#NN    。#PU  体表#NR  银灰度色#VV  ，#PU  无鳞#NN  ，#PU  但#AD  表面#NN  有#VE  一#CD  层#M  银粉#NN  ，#PU  侧浅#AD  在#P  胸鳍#NN  上方#NN  向后#VV  显著#JJ  弯下#NN  沿#P  腹#CD  线#M  直达#VV  尾端#NN  ，#PU  背鳍#AD  极#AD  长#VA  ，#PU  无#VE  腹鳍#NN    。#PU  带鱼#NN  肉#NN  多#CD  且#CC  细#CD  ，#PU  脂肪#AD  较多#VA  且#CC  集中#VV  于#P  体外层#NN  ，#PU  味#NN  鲜美#NN  ，#PU  刺较#AD  少#VA  ，#PU  但#AD  腹部#AD  有#VE  游离#VV  的#DEC  小刺#NN    。#PU  我国#NN  沿海#NN  均#AD  产#VV  ，#PU  以#P  东海#NR  产量#NN  最#AD  大#VA  ，#PU  南海#NR  产量#NN  较#AD  少#VA  ，#PU  浙江#NR  、#PU  山东#NR  沿海#NN  是#VC  产量#NN  较#AD  多#VA  的#DEC  二#CD  个#M  海区#NN    。#PU  11#CD  -#NN  12月#NT  是#VC  盛产#NN  带鱼#NN  的#DEG  季节#NN    。#PU
        </pos>

        <parsing>
            (nn, 带状#NN, 带鱼#NN)  (nn, 带状#NN, 体长#NN)  (nn, 带状#NN, 扁侧呈#NN)  (nsubj, 窄#VA, 带状#NN)  (nsubj, 窄#VA, 头#NN)  (root, ROOT#null, 窄#VA)  (comod, 窄#VA, 长#VA)  (nsubj, 大#VA, 口#NN)  (conj, 窄#VA, 大#VA)  (dep, 大#VA, 且尖#VA)  (nsubj, 锋利#VV, 牙#NR)  (conj, 窄#VA, 锋利#VV)  (nn, 位高#NN, 眼#NN)  (amod, 位高#NN, 大#JJ)  (nsubj, 细#VV, 位高#NN)  (advmod, 细#VV, 尾部#AD)  (ccomp, 锋利#VV, 细#VV)  (dobj, 细#VV, 鞭状#NN)   (nsubj, 银灰度色#VV, 体表#NR)  (root, ROOT#null, 银灰度色#VV)  (nsubj, 有#VE, 无鳞#NN)  (advmod, 有#VE, 但#AD)  (nsubj, 有#VE, 表面#NN)  (ccomp, 银灰度色#VV, 有#VE)  (nummod, 层#M, 一#CD)  (clf, 银粉#NN, 层#M)  (dobj, 有#VE, 银粉#NN)  (advmod, 向后#VV, 侧浅#AD)  (case, 上方#NN, 在#P)  (nn, 上方#NN, 胸鳍#NN)  (prep, 向后#VV, 上方#NN)  (conj, 有#VE, 向后#VV)  (amod, 弯下#NN, 显著#JJ)  (dobj, 向后#VV, 弯下#NN)  (case, 线#M, 沿#P)  (nummod, 线#M, 腹#CD)  (prep, 直达#VV, 线#M)  (conj, 向后#VV, 直达#VV)  (dobj, 直达#VV, 尾端#NN)  (advmod, 长#VA, 背鳍#AD)  (advmod, 长#VA, 极#AD)  (conj, 有#VE, 长#VA)  (conj, 有#VE, 无#VE)  (dobj, 无#VE, 腹鳍#NN)   (nn, 肉#NN, 带鱼#NN)  (nsubj, 较多#VA, 肉#NN)  (nummod, 细#CD, 多#CD)  (cc, 细#CD, 且#CC)  (dep, 较多#VA, 细#CD)  (advmod, 较多#VA, 脂肪#AD)  (root, ROOT#null, 较多#VA)  (cc, 较多#VA, 且#CC)  (dep, 较多#VA, 集中#VV)  (case, 体外层#NN, 于#P)  (prep, 集中#VV, 体外层#NN)  (nn, 鲜美#NN, 味#NN)  (nsubj, 少#VA, 鲜美#NN)  (advmod, 少#VA, 刺较#AD)  (conj, 较多#VA, 少#VA)  (advmod, 有#VE, 但#AD)  (advmod, 有#VE, 腹部#AD)  (conj, 较多#VA, 有#VE)  (relcl, 小刺#NN, 游离#VV)  (mark, 游离#VV, 的#DEC)  (dobj, 有#VE, 小刺#NN)   (nn, 沿海#NN, 我国#NN)  (nsubj, 产#VV, 沿海#NN)  (advmod, 产#VV, 均#AD)  (root, ROOT#null, 产#VV)  (case, 大#VA, 以#P)  (nn, 产量#NN, 东海#NR)  (nsubj, 大#VA, 产量#NN)  (advmod, 大#VA, 最#AD)  (prep, 海区#NN, 大#VA)  (nn, 产量#NN, 南海#NR)  (nsubj, 少#VA, 产量#NN)  (advmod, 少#VA, 较#AD)  (conj, 大#VA, 少#VA)  (conj, 山东#NR, 浙江#NR)  (nn, 沿海#NN, 山东#NR)  (nsubj, 海区#NN, 沿海#NN)  (cop, 海区#NN, 是#VC)  (nsubj, 多#VA, 产量#NN)  (advmod, 多#VA, 较#AD)  (relcl, 海区#NN, 多#VA)  (mark, 多#VA, 的#DEC)  (nummod, 个#M, 二#CD)  (clf, 海区#NN, 个#M)  (ccomp, 产#VV, 海区#NN)   (nummod, -#NN, 11#CD)  (dep, 季节#NN, 12月#NT)  (cop, 季节#NN, 是#VC)  (nn, 带鱼#NN, 盛产#NN)  (assmod, 季节#NN, 带鱼#NN)  (case, 带鱼#NN, 的#DEG)  (root, ROOT#null, 季节#NN)
        </parsing>

        <tag>
            
        </tag>
    </introduction>

    <effect>
        <rawdata>
            1.预防癌症
            带鱼含有丰富的硒，这种矿物质有抗氧化能力，并且对于预防肝病意义重大，足够量的硒摄入可以极大的降低肝癌发病率。
            2.提高智力
            带鱼有一定的脂肪含量，但不高。这些脂肪绝大部分是Omega-3系列多不饱和脂肪，其中包括DHA和EPA，对于脑部发育，提高智力有很好的帮助。
            3.预防心血管疾病
            可以降低血压和血脂，对心血管系统有很好的保护作用，有利于预防高血压、心肌梗死等心血管疾病。常吃带鱼还有养肝补血、泽肤养发健美的功效。
        </rawdata>

        <segment>
            预防  癌症
            带鱼  含有  丰富  的硒  ，  这  种  矿物质  有  抗氧化  能力  ，  并且  对于  预防  肝病  意义  重大  ，  足够  量  的  硒摄入  可以  极  大  的  降低  肝癌  发病率  。
            提高  智力
            带鱼  有  一定  的  脂肪  含量  ，  但  不高  。  这些  脂肪  绝大部分  是  Omega-3  系列  多  不饱和  脂肪  ，  其中  包括  DHA  和  EPA  ，  对于  脑部  发育  ，  提高  智力  有  很  好  的  帮助  。
            预防  心  血管  疾病
            可以  降低  血压  和  血脂  ，  对  心血管  系统  有  很  好  的  保护  作用  ，  有利于  预防  高血压  、  心肌梗死  等  心血管  疾病  。  常  吃  带鱼  还有  养肝  补血  、  泽肤  养  发  健美  的  功效  。
        </segment>

        <pos>
            预防#VV  癌症#NN
            带鱼#NN  含有#AD  丰富#VA  的硒#VA  ，#PU  这#DT  种#M  矿物质#NN  有#VE  抗氧化#NN  能力#NN  ，#PU  并且#CC  对于#P  预防#NN  肝病#NN  意义#NN  重大#VA  ，#PU  足够#JJ  量#NN  的#DEG  硒摄入#NN  可以#VV  极#AD  大#VA  的#DEC  降低#VV  肝癌#NN  发病率#NN  。#PU
            提高#VV  智力#NN
            带鱼#NN  有#VE  一定#JJ  的#DEG  脂肪#NN  含量#NN  ，#PU  但#AD  不高#VV    。#PU  这些#DT  脂肪#NN  绝大部分#NN  是#VC  Omega-3#CD  系列#M  多#CD  不饱和#NN  脂肪#NN  ，#PU  其中#NN  包括#VV  DHA#NN  和#CC  EPA#NN  ，#PU  对于#P  脑部#NN  发育#NN  ，#PU  提高#NN  智力#AD  有#VE  很#AD  好#VA  的#DEC  帮助#NN    。#PU    。#PU
            预防#VV  心#NN  血管#NN  疾病#NN
            可以#VV  降低#VV  血压#CD  和#CC  血脂#CD  ，#PU  对#P  心血管#NN  系统#NN  有#VE  很#AD  好#VA  的#DEC  保护#NN  作用#NN  ，#PU  有利于#VV  预防#VV  高血压#NR  、#PU  心肌梗死#NR  等#ETC  心血管#NN  疾病#NN    。#PU  常#AD  吃#VV  带鱼#NN  还有#AD  养肝#NR  补血#NR  、#PU  泽肤#NR  养#VV  发#VV  健美#NN  的#DEC  功效#NN    。#PU
        </pos>

        <parsing>
            (root, ROOT#null, 预防#VV)  (dobj, 预防#VV, 癌症#NN)
            (nsubj, 丰富#VA, 带鱼#NN)  (advmod, 丰富#VA, 含有#AD)  (root, ROOT#null, 丰富#VA)  (comod, 丰富#VA, 的硒#VA)  (det, 矿物质#NN, 这#DT)  (clf, 这#DT, 种#M)  (dep, 有#VE, 矿物质#NN)  (conj, 丰富#VA, 有#VE)  (nn, 能力#NN, 抗氧化#NN)  (dobj, 有#VE, 能力#NN)  (cc, 有#VE, 并且#CC)  (case, 重大#VA, 对于#P)  (nn, 意义#NN, 预防#NN)  (nn, 意义#NN, 肝病#NN)  (nsubj, 重大#VA, 意义#NN)  (prep, 降低#VV, 重大#VA)  (amod, 量#NN, 足够#JJ)  (assmod, 硒摄入#NN, 量#NN)  (case, 量#NN, 的#DEG)  (nsubj, 降低#VV, 硒摄入#NN)  (mmod, 降低#VV, 可以#VV)  (advmod, 大#VA, 极#AD)  (dvpmod, 降低#VV, 大#VA)  (dep, 大#VA, 的#DEC)  (conj, 有#VE, 降低#VV)  (nn, 发病率#NN, 肝癌#NN)  (dobj, 降低#VV, 发病率#NN)
            (root, ROOT#null, 提高#VV)  (dobj, 提高#VV, 智力#NN)
            (dep, 有#VE, 带鱼#NN)  (root, ROOT#null, 有#VE)  (assmod, 含量#NN, 一定#JJ)  (case, 一定#JJ, 的#DEG)  (nn, 含量#NN, 脂肪#NN)  (nsubj, 不高#VV, 含量#NN)  (advmod, 不高#VV, 但#AD)  (dep, 有#VE, 不高#VV)   (det, 脂肪#NN, 这些#DT)  (nn, 绝大部分#NN, 脂肪#NN)  (nsubj, 脂肪#NN, 绝大部分#NN)  (cop, 脂肪#NN, 是#VC)  (nummod, 系列#M, Omega-3#CD)  (clf, 脂肪#NN, 系列#M)  (nummod, 不饱和#NN, 多#CD)  (nn, 脂肪#NN, 不饱和#NN)  (root, ROOT#null, 脂肪#NN)  (nsubj, 包括#VV, 其中#NN)  (conj, 脂肪#NN, 包括#VV)  (conj, EPA#NN, DHA#NN)  (cc, EPA#NN, 和#CC)  (dobj, 包括#VV, EPA#NN)  (case, 发育#NN, 对于#P)  (nn, 发育#NN, 脑部#NN)  (prep, 有#VE, 发育#NN)  (nsubj, 有#VE, 提高#NN)  (advmod, 有#VE, 智力#AD)  (conj, 脂肪#NN, 有#VE)  (advmod, 好#VA, 很#AD)  (relcl, 帮助#NN, 好#VA)  (mark, 好#VA, 的#DEC)  (dobj, 有#VE, 帮助#NN)   (root, ROOT#null, null#null)
            (root, ROOT#null, 预防#VV)  (nn, 疾病#NN, 心#NN)  (nn, 疾病#NN, 血管#NN)  (dobj, 预防#VV, 疾病#NN)
            (mmod, 降低#VV, 可以#VV)  (root, ROOT#null, 降低#VV)  (nummod, 血脂#CD, 血压#CD)  (cc, 血脂#CD, 和#CC)  (range, 降低#VV, 血脂#CD)  (case, 系统#NN, 对#P)  (nn, 系统#NN, 心血管#NN)  (prep, 有#VE, 系统#NN)  (dep, 降低#VV, 有#VE)  (advmod, 好#VA, 很#AD)  (relcl, 作用#NN, 好#VA)  (mark, 好#VA, 的#DEC)  (nn, 作用#NN, 保护#NN)  (dobj, 有#VE, 作用#NN)  (dep, 降低#VV, 有利于#VV)  (ccomp, 有利于#VV, 预防#VV)  (conj, 心肌梗死#NR, 高血压#NR)  (nn, 疾病#NN, 心肌梗死#NR)  (etc, 心肌梗死#NR, 等#ETC)  (nn, 疾病#NN, 心血管#NN)  (dobj, 预防#VV, 疾病#NN)   (advmod, 吃#VV, 常#AD)  (root, ROOT#null, 吃#VV)  (dobj, 吃#VV, 带鱼#NN)  (advmod, 泽肤#NR, 还有#AD)  (nn, 泽肤#NR, 养肝#NR)  (conj, 泽肤#NR, 补血#NR)  (nsubj, 养#VV, 泽肤#NR)  (dep, 吃#VV, 养#VV)  (relcl, 功效#NN, 发#VV)  (dobj, 发#VV, 健美#NN)  (mark, 发#VV, 的#DEC)  (dobj, 养#VV, 功效#NN)
        </parsing>

        <tag>
            
        </tag>
    </effect>

    <manuleffecttag>
        增强免疫力  辅助降血脂  护肝  辅助降血压  抗癌防癌  解毒  止血  补虚  
    </manuleffecttag>

    <nutrition>
        <rawdata>
            1.带鱼的脂肪含量高于一般鱼类，且多为不饱和脂肪酸，这种脂肪酸的碳链较长，具有降低胆固醇的作用。
            2.带鱼全身的鳞和银白色油脂层中还含有一种抗癌成分6－硫代鸟嘌呤，对辅助治疗白血病、胃癌、淋巴肿瘤等有益。
            3.带鱼含有丰富的镁元素，对心血管系统有很好的保护作用，有利于预防高血压、心肌梗死等心血管疾病。常吃带鱼还有养肝补血、泽肤养发健美的功效。
            4.带鱼中所含的碘，除具有维持甲状腺功能外，还具有促进机体新陈代谢的作用。
        </rawdata>

        <segment>
            带鱼  的  脂肪  含量  高于  一般  鱼类  ，  且  多  为  不  饱和  脂肪酸  ，  这  种  脂肪酸  的  碳链  较  长  ，  具有  降低  胆固醇  的  作用  。
            带鱼  全身  的  鳞和  银白色  油脂  层  中  还  含有  一  种  抗癌  成分  6  －  硫代  鸟嘌呤  ，  对  辅助  治疗  白血病  、  胃癌  、  淋巴  肿瘤  等  有益  。
            带鱼  含有  丰富  的  镁  元素  ，  对  心血管  系统  有  很  好  的  保护  作用  ，  有利于  预防  高血压  、  心肌梗死  等  心血管  疾病  。  常  吃  带鱼  还有  养肝  补血  、  泽肤  养  发  健美  的  功效  。
            带鱼  中  所  含  的碘  ，  除  具有  维持  甲状腺  功能  外  ，  还  具有  促进  机体  新陈代谢  的  作用  。
        </segment>

        <pos>
            带鱼#NN  的#DEG  脂肪#NN  含量#NN  高于#VV  一般#JJ  鱼类#NN  ，#PU  且#CC  多#AD  为#VC  不#AD  饱和#JJ  脂肪酸#NN  ，#PU  这#DT  种#M  脂肪酸#NN  的#DEG  碳链#NN  较#AD  长#VA  ，#PU  具有#VV  降低#VV  胆固醇#NN  的#DEC  作用#NN  。#PU
            带鱼#NN  全身#NN  的#DEG  鳞和#NN  银白色#NN  油脂#CD  层#M  中#LC  还#AD  含有#VV  一#CD  种#M  抗癌#NN  成分#NN  6#CD  －#PU  硫代#CD  鸟嘌呤#NN  ，#PU  对#P  辅助#NN  治疗#NN  白血病#NN  、#PU  胃癌#NN  、#PU  淋巴#NN  肿瘤#NN  等#ETC  有益#VA  。#PU
            带鱼#NN  含有#VV  丰富#VA  的#DEC  镁#NN  元素#NN  ，#PU  对#P  心血管#NN  系统#NN  有#VE  很#AD  好#VA  的#DEC  保护#NN  作用#NN  ，#PU  有利于#VV  预防#VV  高血压#NR  、#PU  心肌梗死#NR  等#ETC  心血管#NN  疾病#NN    。#PU  常#AD  吃#VV  带鱼#NN  还有#AD  养肝#NR  补血#NR  、#PU  泽肤#NR  养#VV  发#VV  健美#NN  的#DEC  功效#NN    。#PU    。#PU
            带鱼#NN  中#LC  所#MSP  含#VV  的碘#NN  ，#PU  除#P  具有#VV  维持#VV  甲状腺#NN  功能#NN  外#LC  ，#PU  还#AD  具有#VV  促进#VV  机体#NN  新陈代谢#NN  的#DEC  作用#NN  。#PU
        </pos>

        <parsing>
            (assmod, 含量#NN, 带鱼#NN)  (case, 带鱼#NN, 的#DEG)  (nn, 含量#NN, 脂肪#NN)  (nsubj, 高于#VV, 含量#NN)  (root, ROOT#null, 高于#VV)  (amod, 鱼类#NN, 一般#JJ)  (dobj, 高于#VV, 鱼类#NN)  (cc, 高于#VV, 且#CC)  (advmod, 脂肪酸#NN, 多#AD)  (cop, 脂肪酸#NN, 为#VC)  (neg, 饱和#JJ, 不#AD)  (amod, 脂肪酸#NN, 饱和#JJ)  (conj, 高于#VV, 脂肪酸#NN)  (det, 脂肪酸#NN, 这#DT)  (clf, 这#DT, 种#M)  (assmod, 碳链#NN, 脂肪酸#NN)  (case, 脂肪酸#NN, 的#DEG)  (nsubj, 长#VA, 碳链#NN)  (advmod, 长#VA, 较#AD)  (conj, 高于#VV, 长#VA)  (conj, 高于#VV, 具有#VV)  (relcl, 作用#NN, 降低#VV)  (dobj, 降低#VV, 胆固醇#NN)  (mark, 降低#VV, 的#DEC)  (dobj, 具有#VV, 作用#NN)
            (nn, 全身#NN, 带鱼#NN)  (assmod, 银白色#NN, 全身#NN)  (case, 全身#NN, 的#DEG)  (nn, 银白色#NN, 鳞和#NN)  (nsubj, 含有#VV, 银白色#NN)  (nummod, 层#M, 油脂#CD)  (loc, 含有#VV, 层#M)  (case, 层#M, 中#LC)  (advmod, 含有#VV, 还#AD)  (root, ROOT#null, 含有#VV)  (nummod, 种#M, 一#CD)  (clf, 成分#NN, 种#M)  (nn, 成分#NN, 抗癌#NN)  (nn, 鸟嘌呤#NN, 成分#NN)  (nummod, 硫代#CD, 6#CD)  (nummod, 鸟嘌呤#NN, 硫代#CD)  (dobj, 含有#VV, 鸟嘌呤#NN)  (case, 肿瘤#NN, 对#P)  (nn, 肿瘤#NN, 辅助#NN)  (nn, 肿瘤#NN, 治疗#NN)  (conj, 肿瘤#NN, 白血病#NN)  (conj, 肿瘤#NN, 胃癌#NN)  (nn, 肿瘤#NN, 淋巴#NN)  (prep, 有益#VA, 肿瘤#NN)  (etc, 肿瘤#NN, 等#ETC)  (conj, 含有#VV, 有益#VA)
            (nsubj, 含有#VV, 带鱼#NN)  (root, ROOT#null, 含有#VV)  (relcl, 元素#NN, 丰富#VA)  (mark, 丰富#VA, 的#DEC)  (nn, 元素#NN, 镁#NN)  (dobj, 含有#VV, 元素#NN)  (case, 系统#NN, 对#P)  (nn, 系统#NN, 心血管#NN)  (prep, 有#VE, 系统#NN)  (conj, 含有#VV, 有#VE)  (advmod, 好#VA, 很#AD)  (relcl, 作用#NN, 好#VA)  (mark, 好#VA, 的#DEC)  (nn, 作用#NN, 保护#NN)  (dobj, 有#VE, 作用#NN)  (conj, 含有#VV, 有利于#VV)  (ccomp, 有利于#VV, 预防#VV)  (conj, 心肌梗死#NR, 高血压#NR)  (nn, 疾病#NN, 心肌梗死#NR)  (etc, 心肌梗死#NR, 等#ETC)  (nn, 疾病#NN, 心血管#NN)  (dobj, 预防#VV, 疾病#NN)   (advmod, 吃#VV, 常#AD)  (root, ROOT#null, 吃#VV)  (dobj, 吃#VV, 带鱼#NN)  (advmod, 泽肤#NR, 还有#AD)  (nn, 泽肤#NR, 养肝#NR)  (conj, 泽肤#NR, 补血#NR)  (nsubj, 养#VV, 泽肤#NR)  (dep, 吃#VV, 养#VV)  (relcl, 功效#NN, 发#VV)  (dobj, 发#VV, 健美#NN)  (mark, 发#VV, 的#DEC)  (dobj, 养#VV, 功效#NN)   (root, ROOT#null, null#null)
            (loc, 含#VV, 带鱼#NN)  (case, 带鱼#NN, 中#LC)  (prtmod, 含#VV, 所#MSP)  (root, ROOT#null, 含#VV)  (dobj, 含#VV, 的碘#NN)  (case, 具有#VV, 除#P)  (prep, 具有#VV, 具有#VV)  (nfincl, 功能#NN, 维持#VV)  (dobj, 维持#VV, 甲状腺#NN)  (dobj, 具有#VV, 功能#NN)  (case, 具有#VV, 外#LC)  (advmod, 具有#VV, 还#AD)  (conj, 含#VV, 具有#VV)  (relcl, 作用#NN, 促进#VV)  (nn, 新陈代谢#NN, 机体#NN)  (dobj, 促进#VV, 新陈代谢#NN)  (mark, 促进#VV, 的#DEC)  (dobj, 具有#VV, 作用#NN)
        </parsing>

        <tag>
            
        </tag>
    </nutrition>

    <cuisine>
        <rawdata>
            带鱼腥气较重，宜红烧，糖醋，不适合清蒸。
        </rawdata>

        <segment>
            带鱼  腥气  较重  ，  宜  红烧  ，  糖醋  ，  不  适合  清蒸  。
        </segment>

        <pos>
            带鱼#NN  腥气#NN  较重#NN  ，#PU  宜#NR  红烧#VV  ，#PU  糖醋#NN  ，#PU  不#AD  适合#VV  清蒸#NN  。#PU
        </pos>

        <parsing>
            (nn, 较重#NN, 带鱼#NN)  (nn, 较重#NN, 腥气#NN)  (nsubj, 红烧#VV, 较重#NN)  (nsubj, 红烧#VV, 宜#NR)  (root, ROOT#null, 红烧#VV)  (nsubj, 适合#VV, 糖醋#NN)  (neg, 适合#VV, 不#AD)  (ccomp, 红烧#VV, 适合#VV)  (dobj, 适合#VV, 清蒸#NN)
        </parsing>

        <tag>
            
        </tag>
    </cuisine>

    <pictureweburl>
        http://s1.cdn.xiangha.com/shicai/201310/100932117976.jpg/MTUweDE1MA
    </pictureweburl>

    <picturelocalurl>

    </picturelocalurl>

</content>
